libro_sql/__init__.py
libro_sql/_version.py
libro_sql/database.py
libro_sql/exception.py
libro_sql/extensions.py
libro_sql/sql_magic.py
libro_sql-0.1.11.dist-info/METADATA
libro_sql-0.1.11.dist-info/WHEEL
libro_sql-0.1.11.dist-info/RECORD
