Metadata-Version: 2.3
Name: libro-sql
Version: 0.1.11
Summary: libro sql
Author-email: brokun <brokun0128@gmail.com>, sunshinesmilelk <1176136681@qq.com>
Requires-Python: >=3.9
Requires-Dist: ipython>=7.34.0
Requires-Dist: libro-core>=0.1.6
Requires-Dist: pandas>=2.0.3
Requires-Dist: psycopg2-binary>=2.9.9
Requires-Dist: pydantic>=2.6.4
Requires-Dist: pymysql>=1.1.1
Requires-Dist: sqlalchemy>=2.0.25
